{
  "client": "Camuzzi Gas Pampeana S.A.",
  "assessment_date": "2025-07-04T03:30:59.960725",
  "version": "1.0",
  "modules": {
    "network": {
      "vpcs": {
        "LA-Santiago": [],
        "LA-Buenos Aires1": [],
        "CN-Hong Kong": [],
        "AP-Bangkok": [],
        "AP-Singapore": []
      },
      "subnets": {
        "LA-Santiago": [],
        "LA-Buenos Aires1": [],
        "CN-Hong Kong": [],
        "AP-Bangkok": [],
        "AP-Singapore": []
      },
      "security_groups": {
        "LA-Santiago": [],
        "LA-Buenos Aires1": [],
        "CN-Hong Kong": [],
        "AP-Bangkok": [],
        "AP-Singapore": []
      },
      "network_acls": {
        "LA-Santiago": [],
        "LA-Buenos Aires1": [],
        "CN-Hong Kong": [],
        "AP-Bangkok": [],
        "AP-Singapore": []
      },
      "elastic_ips": {
        "LA-Santiago": [],
        "LA-Buenos Aires1": [],
        "CN-Hong Kong": [],
        "AP-Bangkok": [],
        "AP-Singapore": []
      },
      "nat_gateways": {},
      "vpn_connections": {},
      "exposed_resources": [],
      "findings": [],
      "statistics": {
        "total_vpcs": 0,
        "total_subnets": 0,
        "total_security_groups": 0,
        "total_elastic_ips": 0,
        "exposed_resources": 0,
        "critical_ports_exposed": 0,
        "unused_elastic_ips": 0,
        "overly_permissive_rules": 0,
        "findings_by_severity": {
          "CRITICAL": 0,
          "HIGH": 0,
          "MEDIUM": 0,
          "LOW": 0
        }
      },
      "timestamp": "2025-07-04T03:30:59.961734"
    },
    "storage": {
      "evs_volumes": {
        "LA-Santiago": [],
        "LA-Buenos Aires1": [],
        "CN-Hong Kong": [],
        "AP-Bangkok": [],
        "AP-Singapore": []
      },
      "obs_buckets": [],
      "backups": {
        "LA-Santiago": [],
        "LA-Buenos Aires1": [],
        "CN-Hong Kong": [],
        "AP-Bangkok": [],
        "AP-Singapore": []
      },
      "sfs_shares": {
        "LA-Santiago": [],
        "LA-Buenos Aires1": [],
        "CN-Hong Kong": [],
        "AP-Bangkok": [],
        "AP-Singapore": []
      },
      "encryption_status": {
        "evs": {
          "encrypted": 0,
          "unencrypted": 0
        },
        "obs": {
          "encrypted": 0,
          "unencrypted": 0
        }
      },
      "findings": [],
      "statistics": {
        "total_evs_volumes": 0,
        "total_obs_buckets": 0,
        "total_backups": 0,
        "encryption_compliance": {
          "evs": 0,
          "obs": 0,
          "overall": 0
        },
        "unattached_volumes": 0,
        "public_buckets": 0,
        "buckets_without_versioning": 0,
        "resources_without_classification": 0,
        "total_storage_gb": 0,
        "findings_by_severity": {
          "CRITICAL": 0,
          "HIGH": 0,
          "MEDIUM": 0,
          "LOW": 0
        }
      },
      "timestamp": "2025-07-04T03:30:59.965733"
    },
    "monitoring": {
      "cloud_eye": {
        "LA-Santiago": {
          "metrics": [],
          "monitored_resources": [],
          "custom_metrics": []
        },
        "LA-Buenos Aires1": {
          "metrics": [],
          "monitored_resources": [],
          "custom_metrics": []
        },
        "CN-Hong Kong": {
          "metrics": [],
          "monitored_resources": [],
          "custom_metrics": []
        },
        "AP-Bangkok": {
          "metrics": [],
          "monitored_resources": [],
          "custom_metrics": []
        },
        "AP-Singapore": {
          "metrics": [],
          "monitored_resources": [],
          "custom_metrics": []
        }
      },
      "cloud_trace": {
        "trackers": [],
        "retention_days": 7,
        "obs_bucket": null,
        "encryption": false,
        "key_events_enabled": false
      },
      "log_tank": {
        "LA-Santiago": {
          "log_groups": [],
          "log_streams": [],
          "log_transfers": []
        },
        "LA-Buenos Aires1": {
          "log_groups": [],
          "log_streams": [],
          "log_transfers": []
        },
        "CN-Hong Kong": {
          "log_groups": [],
          "log_streams": [],
          "log_transfers": []
        },
        "AP-Bangkok": {
          "log_groups": [],
          "log_streams": [],
          "log_transfers": []
        },
        "AP-Singapore": {
          "log_groups": [],
          "log_streams": [],
          "log_transfers": []
        }
      },
      "alarms": {
        "LA-Santiago": [],
        "LA-Buenos Aires1": [],
        "CN-Hong Kong": [],
        "AP-Bangkok": [],
        "AP-Singapore": []
      },
      "metrics_coverage": {
        "LA-Santiago": {
          "ecs": {
            "total": 0,
            "monitored": 0,
            "percentage": 0
          },
          "evs": {
            "total": 0,
            "monitored": 0,
            "percentage": 0
          },
          "rds": {
            "total": 0,
            "monitored": 0,
            "percentage": 0
          },
          "elb": {
            "total": 0,
            "monitored": 0,
            "percentage": 0
          }
        },
        "LA-Buenos Aires1": {
          "ecs": {
            "total": 0,
            "monitored": 0,
            "percentage": 0
          },
          "evs": {
            "total": 0,
            "monitored": 0,
            "percentage": 0
          },
          "rds": {
            "total": 0,
            "monitored": 0,
            "percentage": 0
          },
          "elb": {
            "total": 0,
            "monitored": 0,
            "percentage": 0
          }
        },
        "CN-Hong Kong": {
          "ecs": {
            "total": 0,
            "monitored": 0,
            "percentage": 0
          },
          "evs": {
            "total": 0,
            "monitored": 0,
            "percentage": 0
          },
          "rds": {
            "total": 0,
            "monitored": 0,
            "percentage": 0
          },
          "elb": {
            "total": 0,
            "monitored": 0,
            "percentage": 0
          }
        },
        "AP-Bangkok": {
          "ecs": {
            "total": 0,
            "monitored": 0,
            "percentage": 0
          },
          "evs": {
            "total": 0,
            "monitored": 0,
            "percentage": 0
          },
          "rds": {
            "total": 0,
            "monitored": 0,
            "percentage": 0
          },
          "elb": {
            "total": 0,
            "monitored": 0,
            "percentage": 0
          }
        },
        "AP-Singapore": {
          "ecs": {
            "total": 0,
            "monitored": 0,
            "percentage": 0
          },
          "evs": {
            "total": 0,
            "monitored": 0,
            "percentage": 0
          },
          "rds": {
            "total": 0,
            "monitored": 0,
            "percentage": 0
          },
          "elb": {
            "total": 0,
            "monitored": 0,
            "percentage": 0
          }
        }
      },
      "log_retention": {},
      "audit_trails": [],
      "findings": [],
      "statistics": {
        "total_alarms": 0,
        "total_log_groups": 0,
        "cts_enabled": false,
        "average_log_retention": 0,
        "metrics_coverage": {
          "high": 0,
          "medium": 0,
          "low": 20
        },
        "critical_alarms": 0,
        "findings_by_severity": {
          "CRITICAL": 0,
          "HIGH": 0,
          "MEDIUM": 0,
          "LOW": 0
        }
      },
      "timestamp": "2025-07-04T03:30:59.969660"
    },
    "compliance": {
      "frameworks": {
        "CIS_Huawei_Cloud_1.1": {
          "version": "1.1",
          "sections": {
            "1_iam": {
              "title": "Identity and Access Management",
              "controls": [
                {
                  "control_id": "1.1",
                  "title": "Avoid the use of the root account",
                  "status": "PASS",
                  "evidence": "No recent root account activity detected",
                  "recommendation": "Continue avoiding root account usage"
                },
                {
                  "control_id": "1.2",
                  "title": "Ensure MFA is enabled for all IAM users with console password",
                  "status": "PASS",
                  "evidence": "0 admin users without MFA",
                  "recommendation": "Enable MFA for all privileged users immediately"
                },
                {
                  "control_id": "1.3",
                  "title": "Ensure credentials unused for 90 days or greater are disabled",
                  "status": "PASS",
                  "evidence": "0 keys older than 90 days",
                  "recommendation": "Implement automatic key rotation policy"
                },
                {
                  "control_id": "1.4",
                  "title": "Ensure IAM password policy requires strong passwords",
                  "status": "FAIL",
                  "evidence": "3 policy issues found",
                  "recommendation": "Strengthen password policy according to best practices"
                }
              ]
            },
            "2_logging": {
              "title": "Logging",
              "controls": [
                {
                  "control_id": "2.1",
                  "title": "Ensure CloudTrail is enabled",
                  "status": "FAIL",
                  "evidence": "0 trackers configured",
                  "recommendation": "Enable CloudTrail for all regions"
                },
                {
                  "control_id": "2.2",
                  "title": "Ensure CloudTrail log file validation is enabled",
                  "status": "PASS",
                  "evidence": "0/0 trackers encrypted",
                  "recommendation": "Enable encryption for all audit logs"
                }
              ]
            },
            "3_networking": {
              "title": "Networking",
              "controls": [
                {
                  "control_id": "3.1",
                  "title": "Ensure no security groups allow ingress from 0.0.0.0/0",
                  "status": "PASS",
                  "evidence": "0 overly permissive rules found",
                  "recommendation": "Restrict security group rules to specific IPs"
                },
                {
                  "control_id": "3.2",
                  "title": "Ensure no security groups allow ingress to admin ports",
                  "status": "PASS",
                  "evidence": "0 admin ports exposed",
                  "recommendation": "Use bastion hosts for administrative access"
                }
              ]
            },
            "4_storage": {
              "title": "Storage",
              "controls": [
                {
                  "control_id": "4.1",
                  "title": "Ensure data at rest is encrypted",
                  "status": "PASS",
                  "evidence": "0 unencrypted storage resources",
                  "recommendation": "Enable encryption for all storage resources"
                },
                {
                  "control_id": "4.2",
                  "title": "Ensure S3 bucket access is not public",
                  "status": "PASS",
                  "evidence": "0 public buckets found",
                  "recommendation": "Make all buckets private unless explicitly required"
                }
              ]
            }
          },
          "total_controls": 10,
          "passed_controls": 8,
          "failed_controls": 2,
          "not_applicable": 0,
          "compliance_percentage": 80.0
        },
        "ISO_27001_2022": {
          "version": "2022",
          "domains": {
            "A5": {
              "title": "Organizational controls",
              "controls": []
            },
            "A8": {
              "title": "Asset management",
              "controls": [
                {
                  "id": "A.8.1",
                  "title": "Inventory of assets",
                  "status": "NOT_IMPLEMENTED",
                  "evidence": "Inventario de recursos documentado"
                },
                {
                  "id": "A.8.2",
                  "title": "Information classification",
                  "status": "NOT_APPLICABLE",
                  "evidence": "Tags de clasificación en recursos"
                }
              ]
            },
            "A9": {
              "title": "Access control",
              "controls": []
            },
            "A10": {
              "title": "Cryptography",
              "controls": []
            },
            "A12": {
              "title": "Operations security",
              "controls": []
            }
          },
          "total_controls": 93,
          "implemented": 0,
          "partial": 0,
          "not_implemented": 2,
          "compliance_percentage": 0.0
        },
        "NIST_CSF_2.0": {
          "version": "2.0",
          "functions": {
            "identify": {
              "categories": [
                {
                  "id": "ID.AM",
                  "name": "Asset Management",
                  "score": 0.0,
                  "subcategories": [
                    {
                      "id": "ID.AM-1",
                      "desc": "Physical devices inventoried",
                      "status": "N/A"
                    },
                    {
                      "id": "ID.AM-2",
                      "desc": "Software platforms inventoried",
                      "status": "PASS"
                    },
                    {
                      "id": "ID.AM-3",
                      "desc": "Communication flows mapped",
                      "status": "PARTIAL"
                    },
                    {
                      "id": "ID.AM-5",
                      "desc": "Resources prioritized",
                      "status": "FAIL"
                    }
                  ]
                }
              ],
              "maturity": 0.0
            },
            "protect": {
              "categories": [
                {
                  "id": "PR.AC",
                  "name": "Identity Management and Access Control",
                  "score": 2.5,
                  "subcategories": [
                    {
                      "id": "PR.AC-1",
                      "desc": "Identities and credentials managed",
                      "status": "PARTIAL"
                    },
                    {
                      "id": "PR.AC-4",
                      "desc": "Access permissions managed",
                      "status": "PARTIAL"
                    },
                    {
                      "id": "PR.AC-7",
                      "desc": "Users authenticated",
                      "status": "PASS"
                    }
                  ]
                },
                {
                  "id": "PR.DS",
                  "name": "Data Security",
                  "score": 2.5,
                  "subcategories": [
                    {
                      "id": "PR.DS-1",
                      "desc": "Data-at-rest protected",
                      "status": "PARTIAL"
                    },
                    {
                      "id": "PR.DS-2",
                      "desc": "Data-in-transit protected",
                      "status": "PASS"
                    }
                  ]
                }
              ],
              "maturity": 2.5
            },
            "detect": {
              "categories": [
                {
                  "id": "DE.CM",
                  "name": "Security Continuous Monitoring",
                  "score": 1.25
                }
              ],
              "maturity": 1.25
            },
            "respond": {
              "categories": [],
              "maturity": 0
            },
            "recover": {
              "categories": [],
              "maturity": 0
            }
          },
          "maturity_by_function": {
            "identify": 0.0,
            "protect": 2.5,
            "detect": 1.25
          },
          "overall_maturity": 1.25
        }
      },
      "overall_compliance": 40.0,
      "findings": [
        {
          "id": "COMP-003",
          "severity": "MEDIUM",
          "message": "CIS 1.4 - Política de contraseñas débil",
          "details": {
            "issues": [
              "Longitud mínima insuficiente",
              "No requiere mayúsculas",
              "No requiere números"
            ]
          },
          "timestamp": "2025-07-04T03:30:59.973844",
          "module": "compliance"
        },
        {
          "id": "COMP-004",
          "severity": "CRITICAL",
          "message": "CIS 2.1 - Cloud Trace Service no configurado",
          "details": {},
          "timestamp": "2025-07-04T03:30:59.973940",
          "module": "compliance"
        }
      ],
      "recommendations": [
        {
          "priority": "CRITICAL",
          "title": "Remediar: CIS 2.1 - Cloud Trace Service no configurado",
          "description": "Finding COMP-004 requiere atención inmediata",
          "effort": "Variable",
          "impact": "Muy Alto"
        },
        {
          "priority": "HIGH",
          "title": "Implementar programa de seguridad formal",
          "description": "Establecer políticas, procedimientos y responsabilidades",
          "effort": "Alto",
          "impact": "Transformacional"
        },
        {
          "priority": "HIGH",
          "title": "Automatizar controles de seguridad",
          "description": "Implementar Infrastructure as Code y políticas automatizadas",
          "effort": "Medio",
          "impact": "Alto"
        }
      ],
      "gap_analysis": {
        "critical_gaps": [
          {
            "framework": "CIS",
            "control": "2.1",
            "title": "Ensure CloudTrail is enabled",
            "recommendation": "Enable CloudTrail for all regions"
          }
        ],
        "high_priority_gaps": [],
        "medium_priority_gaps": [
          {
            "framework": "CIS",
            "control": "1.4",
            "title": "Ensure IAM password policy requires strong passwords",
            "recommendation": "Strengthen password policy according to best practices"
          }
        ],
        "quick_wins": []
      },
      "maturity_level": 1.6,
      "timestamp": "2025-07-04T03:30:59.973731"
    }
  },
  "consolidated_findings": [
    {
      "id": "COMP-004",
      "severity": "CRITICAL",
      "message": "CIS 2.1 - Cloud Trace Service no configurado",
      "details": {},
      "timestamp": "2025-07-04T03:30:59.973940",
      "module": "compliance"
    },
    {
      "id": "COMP-003",
      "severity": "MEDIUM",
      "message": "CIS 1.4 - Política de contraseñas débil",
      "details": {
        "issues": [
          "Longitud mínima insuficiente",
          "No requiere mayúsculas",
          "No requiere números"
        ]
      },
      "timestamp": "2025-07-04T03:30:59.973844",
      "module": "compliance"
    }
  ],
  "findings_summary": {
    "total": 2,
    "by_severity": {
      "CRITICAL": 1,
      "HIGH": 0,
      "MEDIUM": 1,
      "LOW": 0
    },
    "by_module": {
      "network": 0,
      "storage": 0,
      "monitoring": 0,
      "compliance": 2
    }
  },
  "risk_analysis": {
    "total_risk_score": 12,
    "normalized_security_score": 40.0,
    "risk_level": "CRÍTICO",
    "maturity_level": 1.6
  },
  "executive_summary": {
    "assessment_scope": {
      "total_resources_analyzed": 0,
      "regions_covered": 0,
      "services_evaluated": 4
    },
    "key_findings": {
      "critical_issues": 1,
      "high_priority_issues": 0,
      "total_findings": 2
    },
    "compliance_status": {
      "overall_compliance": 40.0,
      "maturity_level": 1.6,
      "target_maturity": 3.0
    },
    "top_risks": [
      {
        "finding_id": "COMP-004",
        "severity": "CRITICAL",
        "message": "CIS 2.1 - Cloud Trace Service no configurado",
        "module": "compliance"
      }
    ],
    "immediate_actions_required": []
  }
}